playcode/PlayEntry.py
playcode/__init__.py
playcode/password_make.py
playcode/pycode.py
playcode/test.py
playcode-0.0.6.dist-info/METADATA
playcode-0.0.6.dist-info/WHEEL
playcode-0.0.6.dist-info/top_level.txt
playcode-0.0.6.dist-info/RECORD
