Metadata-Version: 2.1
Name: playcode
Version: 0.0.6
Summary: Creating password
Home-page: https://github.com/sjmin/
Author: Seungjun Min
Author-email: sjmin213@gmail.com
Classifier: Programming Language :: Python :: 3
Classifier: License :: OSI Approved :: MIT License
Classifier: Operating System :: OS Independent
Requires-Python: >=3.6
